odoo9_addon_website_odoo_debranding-9.0.1.0.0-py2.7-nspkg.pth
odoo_addons/website_odoo_debranding/__openerp__.py
odoo_addons/website_odoo_debranding/__init__.py
odoo_addons/website_odoo_debranding/README.rst
odoo_addons/website_odoo_debranding/views/disable_odoo.xml
odoo_addons/website_odoo_debranding/static/description/icon.png
odoo9_addon_website_odoo_debranding-9.0.1.0.0.dist-info/top_level.txt
odoo9_addon_website_odoo_debranding-9.0.1.0.0.dist-info/WHEEL
odoo9_addon_website_odoo_debranding-9.0.1.0.0.dist-info/RECORD
odoo9_addon_website_odoo_debranding-9.0.1.0.0.dist-info/metadata.json
odoo9_addon_website_odoo_debranding-9.0.1.0.0.dist-info/DESCRIPTION.rst
odoo9_addon_website_odoo_debranding-9.0.1.0.0.dist-info/METADATA
odoo9_addon_website_odoo_debranding-9.0.1.0.0.dist-info/namespace_packages.txt
